cognite_typed_functions/__init__.py
cognite_typed_functions/_version.py
cognite_typed_functions/app.py
cognite_typed_functions/base_client.py
cognite_typed_functions/cli.py
cognite_typed_functions/client.py
cognite_typed_functions/client_generation.py
cognite_typed_functions/convert.py
cognite_typed_functions/dependency_registry.py
cognite_typed_functions/formatting.py
cognite_typed_functions/introspection.py
cognite_typed_functions/logger.py
cognite_typed_functions/mcp.py
cognite_typed_functions/models.py
cognite_typed_functions/py.typed
cognite_typed_functions/routing.py
cognite_typed_functions/schema.py
cognite_typed_functions/service.py
cognite_typed_functions/tracer.py
cognite_typed_functions/devserver/__init__.py
cognite_typed_functions/devserver/asgi.py
cognite_typed_functions/devserver/auth.py
cognite_typed_functions/devserver/swagger.py
cognite_typed_functions/templates/__init__.py
cognite_typed_functions/templates/client_template.jinja2
cognite_typed_functions-0.3.2.post51.dev0.dist-info/METADATA
cognite_typed_functions-0.3.2.post51.dev0.dist-info/WHEEL
cognite_typed_functions-0.3.2.post51.dev0.dist-info/entry_points.txt
cognite_typed_functions-0.3.2.post51.dev0.dist-info/licenses/LICENSE
cognite_typed_functions-0.3.2.post51.dev0.dist-info/RECORD
