Metadata-Version: 2.4
Name: cognite-typed-functions
Version: 0.3.2.post51.dev0
Summary: FastAPI-style framework for building type-safe Cognite Functions with automatic OpenAPI schema generation and MCP integration
License-File: LICENSE
Requires-Python: >=3.10
Requires-Dist: cognite-sdk>=7.87.0
Requires-Dist: pydantic>=2.10.5
Requires-Dist: typing-extensions>=4.11.0
Provides-Extra: cli
Requires-Dist: typer>=0.9.0; extra == 'cli'
Requires-Dist: uvicorn>=0.37.0; extra == 'cli'
Provides-Extra: tracing
Requires-Dist: opentelemetry-api>=1.20.0; extra == 'tracing'
Requires-Dist: opentelemetry-exporter-otlp>=1.20.0; extra == 'tracing'
Requires-Dist: opentelemetry-sdk>=1.20.0; extra == 'tracing'
